{
    "!": "thrown when index exists already",
    "body": "{\"settings\":{\"number_of_shards\":4,\"number_of_replicas\":1,\"analysis\":{\"tokenizer\":{\"hangul\":{\"type\":\"seunjeon_tokenizer\",\"decompound\":true,\"deinflect\":true,\"index_eojeol\":true,\"pos_tagging\":false},\"edge_30grams\":{\"type\":\"edge_ngram\",\"min_gram\":1,\"max_gram\":30,\"token_chars\":[\"letter\",\"digit\",\"punctuation\",\"symbol\"]}},\"analyzer\":{\"hangul\":{\"type\":\"custom\",\"tokenizer\":\"hangul\",\"filter\":[\"lowercase\"]},\"autocomplete_case_insensitive\":{\"type\":\"custom\",\"tokenizer\":\"edge_30grams\",\"filter\":[\"lowercase\"]},\"autocomplete_case_sensitive\":{\"type\":\"custom\",\"tokenizer\":\"edge_30grams\",\"filter\":[\"standard\"]}}}},\"mappings\":{\"_doc\":{\"dynamic_templates\":[{\"autocomplete\":{\"path_match\":\"_decomposed.*\",\"mapping\":{\"type\":\"text\",\"analyzer\":\"autocomplete_case_insensitive\",\"search_analyzer\":\"standard\"}}},{\"autocomplete_qwerty\":{\"path_match\":\"_qwerty.*\",\"mapping\":{\"type\":\"text\",\"analyzer\":\"autocomplete_case_sensitive\",\"search_analyzer\":\"whitespace\"}}},{\"string_id\":{\"match_mapping_type\":\"string\",\"match\":\"$id\",\"mapping\":{\"type\":\"keyword\",\"ignore_above\":256}}},{\"strings\":{\"match_mapping_type\":\"string\",\"mapping\":{\"type\":\"text\",\"analyzer\":\"hangul\",\"search_analyzer\":\"hangul\",\"fields\":{\"keyword\":{\"type\":\"keyword\",\"ignore_above\":256}}}}}],\"properties\":{\"@version\":{\"type\":\"keyword\",\"index\":false},\"created_at\":{\"type\":\"date\",\"format\":\"strict_date_optional_time||epoch_millis\"},\"updated_at\":{\"type\":\"date\",\"format\":\"strict_date_optional_time||epoch_millis\"},\"deleted_at\":{\"type\":\"date\",\"format\":\"strict_date_optional_time||epoch_millis\"}}}}}",
    "path": "/test-v4",
    "query": {},
    "response": "{\"error\":{\"root_cause\":[{\"type\":\"resource_already_exists_exception\",\"reason\":\"index [test-v4/menh7_JkTJeXGX6b6EzTnA] already exists\",\"index_uuid\":\"menh7_JkTJeXGX6b6EzTnA\",\"index\":\"test-v4\"}],\"type\":\"resource_already_exists_exception\",\"reason\":\"index [test-v4/menh7_JkTJeXGX6b6EzTnA] already exists\",\"index_uuid\":\"menh7_JkTJeXGX6b6EzTnA\",\"index\":\"test-v4\"},\"status\":400}",
    "statusCode": 400
}
